AUTHORS.md
HISTORY.md
LICENSE
minos/api_gateway/common/__init__.py
minos/api_gateway/common/client/__init__.py
minos/api_gateway/common/client/abc.py
minos/api_gateway/common/client/client.py
minos/api_gateway/common/configuration/__init__.py
minos/api_gateway/common/configuration/config.py
minos/api_gateway/common/exceptions.py
minos/api_gateway/common/importlib.py
minos/api_gateway/common/rest/__init__.py
minos/api_gateway/common/rest/loader.py
minos/api_gateway/common/rest/service.py
minos_apigateway_common-0.0.5.dist-info/LICENSE
minos_apigateway_common-0.0.5.dist-info/WHEEL
minos_apigateway_common-0.0.5.dist-info/METADATA
minos_apigateway_common-0.0.5.dist-info/RECORD
